OrbbecSDK.dll
OrbbecSDK.lib
OrbbecSDKConfig.md
OrbbecSDKConfig.xml
pyorbbecsdk.cp39-win_amd64.pyd
extensions/depthengine/depthengine.dll
extensions/depthengine/depthengine.lib
extensions/filters/FilterProcessor.dll
extensions/filters/ob_priv_filter.dll
extensions/firmwareupdater/firmwareupdater.dll
extensions/frameprocessor/ob_frame_processor.dll
pyorbbecsdk/config/OrbbecSDKConfig.md
pyorbbecsdk/config/OrbbecSDKConfig.xml
pyorbbecsdk/config/multi_device_sync_config.json
pyorbbecsdk/examples/.gitkeep
pyorbbecsdk/examples/README.md
pyorbbecsdk/examples/callback.py
pyorbbecsdk/examples/color.py
pyorbbecsdk/examples/coordinate_transform.py
pyorbbecsdk/examples/depth.py
pyorbbecsdk/examples/depth_work_mode.py
pyorbbecsdk/examples/device_firmware_update.py
pyorbbecsdk/examples/device_optional_depth_presets_update.py
pyorbbecsdk/examples/enumerate.py
pyorbbecsdk/examples/forceip.py
pyorbbecsdk/examples/hdr.py
pyorbbecsdk/examples/hot_plug.py
pyorbbecsdk/examples/hw_d2c_align.py
pyorbbecsdk/examples/imu.py
pyorbbecsdk/examples/infrared.py
pyorbbecsdk/examples/laser_interleave.py
pyorbbecsdk/examples/logger.py
pyorbbecsdk/examples/metadata.py
pyorbbecsdk/examples/multi_device.py
pyorbbecsdk/examples/multi_streams.py
pyorbbecsdk/examples/net_device.py
pyorbbecsdk/examples/playback.py
pyorbbecsdk/examples/point_cloud.py
pyorbbecsdk/examples/post_processing.py
pyorbbecsdk/examples/preset.py
pyorbbecsdk/examples/quick_start.py
pyorbbecsdk/examples/recorder.py
pyorbbecsdk/examples/requirements.txt
pyorbbecsdk/examples/save_image_to_disk.py
pyorbbecsdk/examples/sync_align.py
pyorbbecsdk/examples/two_devices_sync.py
pyorbbecsdk/examples/utils.py
pyorbbecsdk/examples/__pycache__/utils.cpython-310.pyc
pyorbbecsdk/examples/__pycache__/utils.cpython-39.pyc
pyorbbecsdk/examples/object_detection/README.md
pyorbbecsdk/examples/object_detection/coco.names
pyorbbecsdk/examples/object_detection/object_detection_sw_align.py
pyorbbecsdk/examples/object_detection/models/readme.md
pyorbbecsdk2-2.0.15.dist-info/licenses/LICENSE
pyorbbecsdk2-2.0.15.dist-info/METADATA
pyorbbecsdk2-2.0.15.dist-info/WHEEL
pyorbbecsdk2-2.0.15.dist-info/top_level.txt
pyorbbecsdk2-2.0.15.dist-info/RECORD
