Metadata-Version: 2.4
Name: pyorbbecsdk2
Version: 2.0.15
Summary: pyorbbecsdk is a python wrapper for the OrbbecSDK
Author: zhonghong
Author-email: zhonghong@orbbec.com
License-File: LICENSE
Dynamic: author
Dynamic: author-email
Dynamic: description
Dynamic: description-content-type
Dynamic: license-file
Dynamic: summary
